accounts/__init__.py
accounts/auth_backends.py
accounts/forms.py
accounts/models.py
accounts/tests.py
accounts/urls.py
accounts/views.py
accounts/templates/accounts/login.html
accounts/templates/accounts/password_reset_confirm.html
accounts/templates/accounts/password_reset_email.html
accounts/templates/accounts/password_reset_form.html
accounts/templates/accounts/user_form.html
django_accounts_cbv-2.0.dist-info/DESCRIPTION.rst
django_accounts_cbv-2.0.dist-info/METADATA
django_accounts_cbv-2.0.dist-info/metadata.json
django_accounts_cbv-2.0.dist-info/RECORD
django_accounts_cbv-2.0.dist-info/top_level.txt
django_accounts_cbv-2.0.dist-info/WHEEL
