Metadata-Version: 2.0
Name: django-accounts-cbv
Version: 2.0
Summary: Account login, logout, and password reset.
Home-page: https://bitbucket.org/nextscreenlabs/django-accounts
Author: Jason Christa
Author-email: jason@zeitcode.com
License: UNKNOWN
Platform: UNKNOWN
Classifier: Environment :: Web Environment
Classifier: License :: OSI Approved :: BSD License
Classifier: Framework :: Django
Classifier: Programming Language :: Python
Requires-Dist: Django (>=1.7)
